{"dataset":"brownfield-land","datetime":"2019-11-22T15:29:46.079736","elapsed":"0.458","organisation":"local-authority-eng:GRT","request-headers":{"Accept":"*/*","Accept-Encoding":"gzip, deflate","Connection":"keep-alive","User-Agent":"Digital Land data collector"},"resource":"b83669edd1f754a74f982e7ba496a689583e3a5a6d6d58962e02e72d6d4e70bb","response-headers":{"Accept-Ranges":"bytes","Cache-Control":"private","Content-Length":"36517","Content-Type":"text/csv","Date":"Fri, 22 Nov 2019 15:29:47 GMT","ETag":"77B41A26F6F374190F6B63AA7ED83987","Expires":"Fri, 20 Dec 2019 00:01:48 GMT","Last-Modified":"Tue, 15 Jan 2019 16:52:48 GMT","Server":"","Vary":"If-Modified-Since, If-None-Match","X-Content-Type-Options":"nosniff","X-Frame-Options":"SAMEORIGIN","X-XSS-Protection":"1; mode=block"},"status":"200","url":"https://www.guildford.gov.uk/media/26733/Guildford-Borough-Council-Brownfield-Land-Register-December-2017-csv-format-/CSV/guildford_brownfieldregister_2017_12_12_rev11"}