{"dataset":"brownfield-land","datetime":"2019-10-26T00:00:25.625Z","elapsed":"5.848137534999987","organisation":"local-authority-eng:DEB","request-headers":{"Accept":"*/*","Accept-Encoding":"gzip, deflate","Connection":"keep-alive","User-Agent":"Digital Land data collector"},"response-headers":{"date":"Sat, 26 Oct 2019 00:00:25 GMT","server":"Apache","x-content-type-options":"nosniff","last-modified":"Tue, 12 Dec 2017 11:01:39 GMT","accept-ranges":"bytes","content-length":"21874","cache-control":"max-age=2592000","expires":"Mon, 25 Nov 2019 00:00:25 GMT","connection":"close","content-type":"text/csv"},"status":"200","url":"http://www.derbyshiredales.gov.uk/images/documents/B/Register%20v7%20Govt%20guidance%2028th%20July%202017.csv","resource":"db3cf1c85effe6e0a4b87502581d21c46e79e3b6d1ed5074bc0469963be46df7"}