{"dataset":"brownfield-land","datetime":"2020-10-07T00:16:20.542781","elapsed":"0.623","organisation":"local-authority-eng:HAG","request-headers":{"Accept":"*/*","Accept-Encoding":"gzip, deflate","Connection":"keep-alive","User-Agent":"Digital Land data collector"},"resource":"e74aa67d877102504e1598111692480f8078944b8e542b46343d38e38027506c","response-headers":{"CF-Cache-Status":"DYNAMIC","CF-RAY":"5de36ed0ac8eeab2-IAD","Cache-Control":"must-revalidate, post-check=0, pre-check=0","Connection":"keep-alive","Content-Disposition":"attachment; filename=\"Brownfield_land_register.csv\"","Content-Length":"45149","Content-Type":"application/vnd.ms-excel","Date":"Wed, 07 Oct 2020 00:16:21 GMT","Expect-CT":"max-age=604800, report-uri=\"https://report-uri.cloudflare.com/cdn-cgi/beacon/expect-ct\"","Expires":"Mon, 26 Jul 1997 05:00:00 GMT","Node":"jadu-web-1","Pragma":"public","Server":"cloudflare","Set-Cookie":"__cfduid=df01cfb9a8a97b7f8c5354dfd56b9a62c1602029780; expires=Fri, 06-Nov-20 00:16:20 GMT; path=/; domain=.harrogate.gov.uk; HttpOnly; SameSite=Lax, PHPSESSID=6p61BCd4TXE4nZw10VkMEjYGUciA-xgK4AWdQiQqcx-O9QS1w1ygVm0CKTqkuYZJ; path=/; secure; HttpOnly, TestCookie=Test; path=/; domain=www.harrogate.gov.uk; HttpOnly","Strict-Transport-Security":"max-age=2592000","X-Content-Type-Options":"nosniff","X-Frame-Options":"SAMEORIGIN","X-XSS-Protection":"1; mode=block","cf-request-id":"05a203966a0000eab210bff200000001"},"status":"200","url":"https://www.harrogate.gov.uk/download/downloads/id/3132/brownfield_land_register.csv"}