{"dataset":"brownfield-land","datetime":"2020-08-20T00:13:58.516667","elapsed":"0.631","organisation":"local-authority-eng:HAG","request-headers":{"Accept":"*/*","Accept-Encoding":"gzip, deflate","Connection":"keep-alive","User-Agent":"Digital Land data collector"},"resource":"e74aa67d877102504e1598111692480f8078944b8e542b46343d38e38027506c","response-headers":{"CF-Cache-Status":"DYNAMIC","CF-RAY":"5c57e958e91f74cb-IAD","Cache-Control":"must-revalidate, post-check=0, pre-check=0","Connection":"keep-alive","Content-Disposition":"attachment; filename=\"Brownfield_land_register.csv\"","Content-Length":"45149","Content-Type":"application/vnd.ms-excel","Date":"Thu, 20 Aug 2020 00:13:58 GMT","Expect-CT":"max-age=604800, report-uri=\"https://report-uri.cloudflare.com/cdn-cgi/beacon/expect-ct\"","Expires":"Mon, 26 Jul 1997 05:00:00 GMT","Node":"jadu-web-1","Pragma":"public","Server":"cloudflare","Set-Cookie":"__cfduid=de7dd92783ade4ac66fa52c3a087baa7c1597882438; expires=Sat, 19-Sep-20 00:13:58 GMT; path=/; domain=.harrogate.gov.uk; HttpOnly; SameSite=Lax, PHPSESSID=4BqIY3-6GDs9XKEXlo%2CS0C93c2b%2CcG5a8XBYSvfwdNdZKBihxpy-pcagltircEie; path=/; secure; HttpOnly, TestCookie=Test; path=/; domain=www.harrogate.gov.uk; HttpOnly","Strict-Transport-Security":"max-age=2592000","X-Content-Type-Options":"nosniff","X-Frame-Options":"SAMEORIGIN","X-XSS-Protection":"1; mode=block","cf-request-id":"04aad02b91000074cb0bb3d200000001"},"status":"200","url":"https://www.harrogate.gov.uk/download/downloads/id/3132/brownfield_land_register.csv"}