{"dataset":"brownfield-land","datetime":"2020-05-14T00:09:50.881573","elapsed":"0.12","organisation":"local-authority-eng:NSM","request-headers":{"Accept":"*/*","Accept-Encoding":"gzip, deflate","Connection":"keep-alive","User-Agent":"Digital Land data collector"},"resource":"da98a951d37e6a2fff10956c22c5fbbc0314e8304a002104a235db896b50fcec","response-headers":{"Accept-Ranges":"bytes","Age":"0","Connection":"keep-alive","Content-Length":"27288","Content-Type":"text/csv","Date":"Thu, 14 May 2020 00:09:51 GMT","Etag":"\"5e0a9741-6a98\"","Last-Modified":"Tue, 31 Dec 2019 00:33:05 GMT","Server":"nginx","Strict-Transport-Security":"max-age=300","Via":"1.1 varnish","X-Cache":"MISS, MISS","X-Cache-Hits":"0, 0","X-Pantheon-Styx-Hostname":"styx-fe1-a-789d66bff9-57rpt","X-Served-By":"cache-mdw17383-MDW, cache-bwi5040-BWI","X-Styx-Req-Id":"3ad9939e-9577-11ea-adc9-32a9102b2f0a","X-Timer":"S1589414991.904876,VS0,VE98"},"status":"200","url":"https://www.n-somerset.gov.uk/wp-content/uploads/2019/12/brownfield-sites.csv"}