{"dataset":"brownfield-land","datetime":"2020-10-21T00:25:29.487838","elapsed":"0.52","organisation":"national-park-authority:Q72617988","request-headers":{"Accept":"*/*","Accept-Encoding":"gzip, deflate","Connection":"keep-alive","User-Agent":"Digital Land data collector"},"resource":"836f862dcf5faa6ccb6e894863528164de8daea0156cdf2157bce9722a636b31","response-headers":{"Accept-Ranges":"bytes","Age":"11362","Cache-Control":"stale-if-error=2592000, max-age=2592000","Connection":"keep-alive","Content-Type":"application/octet-stream","Date":"Tue, 20 Oct 2020 21:16:07 GMT","ETag":"\"5e5a439c-b23\"","Expires":"Thu, 19 Nov 2020 21:16:07 GMT","Last-Modified":"Sat, 29 Feb 2020 10:57:32 GMT","Server":"openresty","Transfer-Encoding":"chunked","Via":"1.1 np-web01.ash2.squiz.cloud","X-Cache":"HIT from np-web01.ash2.squiz.cloud","X-Content-Type-Options":"nosniff","X-Request-ID":"90aa29bd-6204-40c7-b20d-209d8e374aba"},"status":"200","url":"https://www.peakdistrict.gov.uk/__data/assets/file/0026/81683/pdnpa-blr-18_12_2017.csv"}