{"dataset":"brownfield-land","datetime":"2020-07-02T00:19:08.142566","elapsed":"1.755","organisation":"local-authority-eng:SWK","request-headers":{"Accept":"*/*","Accept-Encoding":"gzip, deflate","Connection":"keep-alive","User-Agent":"Digital Land data collector"},"resource":"69584001774ee43f8bc3e6df5517c2b8eb3109bcb6db5e1e5103e9ff594f2c22","response-headers":{"Cache-Control":"private","Content-Disposition":"attachment; filename=\"Southwark Brownfield 2020.xlsx\"","Content-Length":"2467148","Content-Type":"application/vnd.openxmlformats-officedocument.spreadsheetml.sheet","Date":"Thu, 02 Jul 2020 00:18:58 GMT","Set-Cookie":"visid_incap_1892657=B4EXcE49RfinQD/GSRN1Lvsn/V4AAAAAQUIPAAAAAACvJ5g5rC8+uBEgrj5ckgE8; expires=Thu, 01 Jul 2021 11:47:47 GMT; HttpOnly; path=/; Domain=.southwark.gov.uk, incap_ses_486_1892657=hNKyVI9bcQyUGad2f56+Bvwn/V4AAAAApM1PUGtecWTB2qgi6UyCzQ==; path=/; Domain=.southwark.gov.uk","X-CDN":"Incapsula","X-Iinfo":"1-24367043-24367044 NNNN CT(85 277 0) RT(1593649147370 16) q(0 0 4 0) r(7 8) U2","X-Powered-By":"ASP.NET"},"status":"200","url":"https://www.southwark.gov.uk/assets/attach/5763/Southwark-Brownfield-2020.xlsx"}