{"dataset":"brownfield-land","datetime":"2020-08-30T00:20:18.406109","elapsed":"0.52","organisation":"local-authority-eng:TRF","request-headers":{"Accept":"*/*","Accept-Encoding":"gzip, deflate","Connection":"keep-alive","User-Agent":"Digital Land data collector"},"resource":"a521f3ce21689423001a5b7739a1a3f1f05ac746bf1819f875a4574513f5ebb5","response-headers":{"Accept-Ranges":"bytes","Content-Length":"23315","Content-Type":"text/csv","Date":"Sun, 30 Aug 2020 00:20:19 GMT","ETag":"\"5f1ae60b98cc6569e7d019cbf7fa863c\"","Last-Modified":"Tue, 31 Jul 2018 16:13:13 GMT","Server":"AmazonS3","x-amz-id-2":"9rnzHKk9NmbipSOiIPc7SUo2bFrOHIagQYKdwgwigpw9LC4GgsYURuWVUM4mmZvsgzGX/lr6pxk=","x-amz-request-id":"9C30E137C4536F80"},"status":"200","url":"https://s3.eu-west-2.amazonaws.com/digital-land/brownfield-sites/trafford-2017-12-22-rev1.csv"}