{"dataset":"brownfield-land","datetime":"2020-04-10T00:09:41.377642","elapsed":"0.34","organisation":"local-authority-eng:RUH","request-headers":{"Accept":"*/*","Accept-Encoding":"gzip, deflate","Connection":"keep-alive","User-Agent":"Digital Land data collector"},"resource":"2e282ea34c1197bd5c33f6fb21fb8d0c3c0f8c973745b70d8d840573b5a5d4db","response-headers":{"Accept-Ranges":"bytes","Connection":"Keep-Alive","Content-Encoding":"gzip","Content-Length":"3044","Content-Type":"application/octet-stream","Date":"Fri, 10 Apr 2020 00:09:45 GMT","Keep-Alive":"timeout=15, max=100","Last-Modified":"Thu, 09 Apr 2020 07:30:13 GMT","Server":"Apache","Vary":"Accept-Encoding"},"status":"200","url":"http://data.rushmoor.gov.uk/Datasets/Open/Brownfield%20Register/rushmoor_brownfieldregister_2017-12-11_rev1.csv"}