{"dataset":"brownfield-land","datetime":"2020-05-12T00:10:11.051544","elapsed":"0.076","organisation":"development-corporation:Q20648596","request-headers":{"Accept":"*/*","Accept-Encoding":"gzip, deflate","Connection":"keep-alive","User-Agent":"Digital Land data collector"},"resource":"f1e218c96f99e378fdbaed9a426c6b44d0e7d3b5fec63e201625047643c6da74","response-headers":{"Accept-Ranges":"bytes","Access-Control-Allow-Origin":"*","Age":"431090","CF-Cache-Status":"HIT","CF-RAY":"591fea4b4c7acf38-IAD","Cache-Control":"max-age=1209600","Connection":"keep-alive","Content-Length":"17258","Content-Type":"text/csv","Date":"Tue, 12 May 2020 00:10:11 GMT","Expect-CT":"max-age=604800, report-uri=\"https://report-uri.cloudflare.com/cdn-cgi/beacon/expect-ct\"","Expires":"Tue, 19 May 2020 23:09:35 GMT","Grace":"none","Server":"cloudflare","Set-Cookie":"__cfduid=d19776414b0fdd97bcd496acd45d8850f1589242211; expires=Thu, 11-Jun-20 00:10:11 GMT; path=/; domain=.london.gov.uk; HttpOnly; SameSite=Lax","Vary":"Accept-Encoding","Via":"1.1 varnish-v4","X-Content-Type-Options":"nosniff","X-DC":"","X-Varnish":"8819289 442824","X-Varnish-Cache":"HIT","cf-request-id":"02a7d0c3100000cf387008a200000001"},"status":"200","url":"https://www.london.gov.uk/sites/default/files/opdc_brownfieldlandregister_jan2018.csv"}