{"dataset":"brownfield-land","datetime":"2019-11-25T06:48:42.981821","elapsed":"0.784","organisation":"national-park-authority:Q4972284","request-headers":{"Accept":"*/*","Accept-Encoding":"gzip, deflate","Connection":"keep-alive","User-Agent":"Digital Land data collector"},"response-headers":{"Cache-Control":"private, must-revalidate","Connection":"keep-alive","Content-Encoding":"gzip","Content-Type":"text/html; charset=utf-8","Date":"Mon, 25 Nov 2019 06:48:43 GMT","Server":"openresty","Set-Cookie":"SQ_SYSTEM_SESSION=0n869j33dbfnefj2b56dk2mjerjdpd62pidv585q5kncdpt7hgo3b5llsl0s7lfap10f0bsn9r7oh087sdm4hrceetj3ca31bar5n00; path=/","Transfer-Encoding":"chunked","Vary":"Accept-Encoding","X-Cache":"MISS from np2-web01","X-Cache-Lookup":"MISS from np2-web01:3128","X-Content-Type-Options":"nosniff","X-Frame-Options":"SAMEORIGIN","X-upgrade-enabled":"off"},"status":"404","url":"http://www.broads-authority.gov.uk/__data/assets/text_file/0004/1064128/broads_authority_brownfieldregister_2017-12-13_rev1.csv"}