{"dataset":"brownfield-land","datetime":"2019-12-18T12:06:16.789341","elapsed":"1.073","organisation":"local-authority-eng:BIR","request-headers":{"Accept":"*/*","Accept-Encoding":"gzip, deflate","Connection":"keep-alive","User-Agent":"Digital Land data collector"},"resource":"586fd8bf0779012ac7c4b8681341b640e538deeaaf5529b2363862253b528703","response-headers":{"Cache-Control":"must-revalidate, post-check=0, pre-check=0","Connection":"Keep-Alive","Content-Disposition":"attachment; filename=\"birmingham_brownfieldregister_20180921_rev1.csv\"","Content-Length":"163867","Content-Type":"application/vnd.ms-excel","Date":"Wed, 18 Dec 2019 12:06:17 GMT","Expires":"Sat, 26 Jul 1997 05:00:00 GMT","Keep-Alive":"timeout=5, max=98","Pragma":"public","Set-Cookie":"m6jA1MEzDRPHIVj5=ac4675803c1af76ad9b0032d08633c25; path=/; secure; HttpOnly, TestCookie=Test; path=/; domain=www.birmingham.gov.uk; secure; HttpOnly, TS01fe61fd=0184cb26e9006e7cc289aadc71831fbfae181f3344622380ef4cc6974beedaf2bc0d40181c9e6916b5a1f47f80d56d655c8cf36b5b; Path=/; Secure; HTTPOnly, TS01be1219=0184cb26e9d56705130366f9b97f8cb6c82943bdc9f7e6aeb83ebc0a54d43bde218b94277e24a72e22f84d4cca29484fc017ea7401; path=/; domain=www.birmingham.gov.uk; HTTPonly; Secure","Strict-Transport-Security":"max-age=2592000","Vary":"Host","Via":"1.1 lon1-bit13","X-Content-Type-Options":"nosniff","X-Frame-Options":"SAMEORIGIN","X-XSS-Protection":"1; mode=block"},"status":"200","url":"https://www.birmingham.gov.uk/download/downloads/id/9037/brownfield_register.csv"}