{"dataset":"brownfield-land","datetime":"2020-04-08T08:25:07.316409","elapsed":"2.704","organisation":"national-park-authority:Q72617988","request-headers":{"Accept":"*/*","Accept-Encoding":"gzip, deflate","Connection":"keep-alive","User-Agent":"Digital Land data collector"},"response-headers":{"Cache-Control":"private, max-age=0","Connection":"keep-alive","Content-Encoding":"gzip","Content-Type":"text/html; charset=utf-8","Date":"Wed, 08 Apr 2020 08:25:09 GMT","Expires":"Wed, 08 Apr 2020 09:25:08 GMT","Pragma":"cache","Server":"openresty","Set-Cookie":"SQ_SYSTEM_SESSION=lac6obtka7dvs232htg02hqn08qmbemm1at692e13s5quhehbat4j405o3gq46u8g1g171u73e45dh1k4sou0nrodeft0sunr657th1; path=/; secure; HttpOnly","Transfer-Encoding":"chunked","Vary":"Accept-Encoding, Accept-Encoding","Via":"1.1 np-web01.ash2.squiz.cloud","X-Cache":"MISS from np-web01.ash2.squiz.cloud","X-Content-Type-Options":"nosniff","X-Frame-Options":"SAMEORIGIN","X-Request-ID":"9714f756-3704-44a6-b47e-2d3b5ef790ec","X-upgrade-enabled":"off"},"status":"404","url":"https://www.peakdistrict.gov.uk/__data/assets/file/0003/1068042/pdnpa-blr-18_12_2017.csv"}