{"dataset":"brownfield-land","datetime":"2020-07-14T00:16:13.151961","elapsed":"0.801","organisation":"local-authority-eng:GRY","request-headers":{"Accept":"*/*","Accept-Encoding":"gzip, deflate","Connection":"keep-alive","User-Agent":"Digital Land data collector"},"response-headers":{"Cache-Control":"private","Content-Length":"16255","Content-Type":"text/html; charset=utf-8","Date":"Tue, 14 Jul 2020 00:16:13 GMT","Expires":"Tue, 14 Jul 2020 00:16:13 GMT","Pragma":"no-cache","Server":"Microsoft-IIS/8.5","Set-Cookie":"ASP.NET_SessionId=k5l4uukqtzmzydy23gnkr2mo; path=/; HttpOnly; SameSite=Lax, clientvars=c8726c7d-a738-4ffe-b841-39a972f4da7f; path=/; HttpOnly, TextOnlyX=; expires=Tue, 14-Jul-2015 00:16:13 GMT; path=/, mode=0; expires=Wed, 21-Oct-2020 00:16:13 GMT; path=/","X-Powered-By":"ASP.NET"},"status":"404","url":"https://www.great-yarmouth.gov.uk/CHttpHandler.ashx?id=2608&p=0"}