{"dataset":"brownfield-land","datetime":"2019-11-30T10:27:38.130826","elapsed":"0.632","organisation":"local-authority-eng:SFT","request-headers":{"Accept":"*/*","Accept-Encoding":"gzip, deflate","Connection":"keep-alive","User-Agent":"Digital Land data collector"},"resource":"9a3ad29f571004785999d4d310a16ee47c6e318c628ec504f3740c2a781f0a1a","response-headers":{"Accept-Ranges":"bytes","Content-Length":"34066","Content-Type":"application/octet-stream","Date":"Sat, 30 Nov 2019 10:27:38 GMT","ETag":"\"c1ff79a7c450d41:0\"","Last-Modified":"Thu, 20 Sep 2018 09:31:05 GMT","Server":"Microsoft-IIS/10.0","Set-Cookie":"ARRAffinity=74b7fce940421b49f9f634d3ab44a809803a3e6d50fd4a2fdcee53d07a7be865;Path=/;HttpOnly;Domain=www.sefton.gov.uk","X-Powered-By":"ASP.NET"},"status":"200","url":"https://www.sefton.gov.uk/media/1363896/Sefton-Brownfield-Land-Register-2017-Pt1.csv"}