{"dataset":"brownfield-land","datetime":"2020-04-29T00:04:14.737898","elapsed":"0.046","organisation":"development-corporation:Q20648596","request-headers":{"Accept":"*/*","Accept-Encoding":"gzip, deflate","Connection":"keep-alive","User-Agent":"Digital Land data collector"},"resource":"f1e218c96f99e378fdbaed9a426c6b44d0e7d3b5fec63e201625047643c6da74","response-headers":{"Access-Control-Allow-Origin":"*","Age":"86405","CF-Cache-Status":"HIT","CF-RAY":"58b4c3b85c2bc198-IAD","Cache-Control":"max-age=1209600","Connection":"keep-alive","Content-Type":"text/csv","Date":"Wed, 29 Apr 2020 00:04:14 GMT","Expect-CT":"max-age=604800, report-uri=\"https://report-uri.cloudflare.com/cdn-cgi/beacon/expect-ct\"","Expires":"Tue, 12 May 2020 00:04:09 GMT","Grace":"none","Server":"cloudflare","Set-Cookie":"__cfduid=de1714e9c21b3446b7022df557442a3c91588118654; expires=Fri, 29-May-20 00:04:14 GMT; path=/; domain=.london.gov.uk; HttpOnly; SameSite=Lax","Transfer-Encoding":"chunked","Vary":"Accept-Encoding","Via":"1.1 varnish-v4","X-Content-Type-Options":"nosniff","X-DC":"","X-Varnish":"659027","X-Varnish-Cache":"MISS","cf-request-id":"0264d8a7330000c198d180d200000001"},"status":"200","url":"https://www.london.gov.uk/sites/default/files/opdc_brownfieldlandregister_jan2018.csv"}