{"dataset":"brownfield-land","datetime":"2020-11-07T00:11:47.454959","elapsed":"0.853","organisation":"local-authority-eng:COV","request-headers":{"Accept":"*/*","Accept-Encoding":"gzip, deflate","Connection":"keep-alive","User-Agent":"Digital Land data collector"},"resource":"ec1ff31625d546423b174d6e6eafca40efa4f10525199b0cbc6990ceb7d748a9","response-headers":{"CF-Cache-Status":"DYNAMIC","CF-RAY":"5ee2d6c87f0b7497-IAD","Cache-Control":"must-revalidate, post-check=0, pre-check=0","Connection":"keep-alive","Content-Disposition":"attachment; filename=\"BrownfieldLandRegister.xlsm\"","Content-Length":"91177","Content-Type":"application/vnd.ms-excel.sheet.macroenabled.12","Date":"Sat, 07 Nov 2020 00:11:48 GMT","ETag":"\"16429-58346a7940b80\"","Expect-CT":"max-age=604800, report-uri=\"https://report-uri.cloudflare.com/cdn-cgi/beacon/expect-ct\"","Expires":"Mon, 26 Jul 1997 05:00:00 GMT","Last-Modified":"Mon, 04 Mar 2019 15:46:06 GMT","Node":"jadu-web-1","Pragma":"no-cache","Server":"cloudflare","Set-Cookie":"__cfduid=dc848df7deb2e27d0674613c47088d6f51604707907; expires=Mon, 07-Dec-20 00:11:47 GMT; path=/; domain=.coventry.gov.uk; HttpOnly; SameSite=Lax, PHPSESSID=%2CSCfsJlcOeCKP43QpnPJaoMQ9PjpZstjneJQHdX4bvh3v6GKWElXslL66HH3M3pH; path=/; secure; HttpOnly, TestCookie=Test; path=/; domain=www.coventry.gov.uk; HttpOnly","Strict-Transport-Security":"max-age=2592000","X-Content-Type-Options":"nosniff","X-Frame-Options":"SAMEORIGIN","X-XSS-Protection":"1; mode=block","cf-request-id":"0641a4914b000074970b9ea000000001"},"status":"200","url":"https://www.coventry.gov.uk/download/downloads/id/27571/brownfield_land_register.xlsm"}