{"dataset":"brownfield-land","datetime":"2020-03-15T00:12:00.404262","elapsed":"0.297","organisation":"local-authority-eng:SNO","request-headers":{"Accept":"*/*","Accept-Encoding":"gzip, deflate","Connection":"keep-alive","User-Agent":"Digital Land data collector"},"resource":"671862da7b7345ad6019817cd796a866fa1f09a5c809873cb33e63436474041f","response-headers":{"Accept-Ranges":"bytes","Age":"12401","Cache-Control":"max-age=1209600","Connection":"keep-alive","Content-Length":"6489","Content-Type":"text/csv","Date":"Sun, 15 Mar 2020 00:12:00 GMT","Expires":"Sat, 28 Mar 2020 20:45:19 GMT","Last-Modified":"Fri, 08 Feb 2019 14:34:08 GMT","Server":"nginx","Via":"varnish","X-AH-Environment":"prod","X-Cache":"HIT","X-Cache-Hits":"2","X-Content-Type-Options":"nosniff","X-Request-ID":"v-b7ba99a4-6634-11ea-a88d-2b4fa03bf824"},"status":"200","url":"https://www.south-norfolk.gov.uk/sites/default/files/downloads/southnorfolk_brownfieldregister_2018-12-31_0.csv"}