{"dataset":"brownfield-land","datetime":"2020-10-16T10:11:26.938063","elapsed":"0.701","organisation":"local-authority-eng:LND","request-headers":{"Accept":"*/*","Accept-Encoding":"gzip, deflate","Connection":"keep-alive","User-Agent":"Digital Land data collector"},"response-headers":{"CF-Cache-Status":"EXPIRED","CF-RAY":"5e30feee29eb2520-IAD","Connection":"keep-alive","Content-Encoding":"gzip","Content-Type":"text/html; charset=utf-8","Date":"Fri, 16 Oct 2020 10:11:27 GMT","Expect-CT":"max-age=604800, report-uri=\"https://report-uri.cloudflare.com/cdn-cgi/beacon/expect-ct\"","Referrer-Policy":"strict-origin-when-cross-origin","Server":"cloudflare","Set-Cookie":"__cfduid=d0d6402aaa56efb13261cf5323451d8891602843087; expires=Sun, 15-Nov-20 10:11:27 GMT; path=/; domain=.cityoflondon.gov.uk; HttpOnly; SameSite=Lax","Strict-Transport-Security":"max-age=15768000","Transfer-Encoding":"chunked","Vary":"Accept-Encoding","X-Content-Type-Options":"nosniff","X-Server-Name":"z-cityoflondon-CACHE1","X-Varnish":"34246412","X-XSS-Protection":"1;mode=block","cf-request-id":"05d27da8d7000025208f307000000001"},"status":"404","url":"https://www.cityoflondon.gov.uk/services/environment-and-planning/planning/development-and-population-information/Documents/city-of-london_brownfieldregister_2018-11-28_update.csv"}