{"dataset":"brownfield-land","datetime":"2020-11-18T00:10:56.710833","elapsed":"1.236","organisation":"local-authority-eng:BIR","request-headers":{"Accept":"*/*","Accept-Encoding":"gzip, deflate","Connection":"keep-alive","User-Agent":"Digital Land data collector"},"resource":"77da1087f91eafee42797dbaa9bebef573d2eb759b39d9db130c99d34cbe4ec4","response-headers":{"Cache-Control":"must-revalidate, post-check=0, pre-check=0","Connection":"Keep-Alive","Content-Disposition":"attachment; filename=\"Brownfield_Register_2019.csv\"","Content-Length":"293977","Content-Type":"application/vnd.ms-excel","Date":"Wed, 18 Nov 2020 00:10:57 GMT","Expires":"Sat, 26 Jul 1997 05:00:00 GMT","Keep-Alive":"timeout=5, max=100","Pragma":"public","Set-Cookie":"m6jA1MEzDRPHIVj5=27d880238593b011190695a23d42550f; path=/; secure; HttpOnly; HttpOnly;SameSite=None; Secure, TestCookie=Test; path=/; domain=www.birmingham.gov.uk; secure; HttpOnly; HttpOnly;SameSite=None; Secure, TS01fe61fd=017a3955152ae8ff3c7c4f62d0c7775b2e8154b5ef6d1d1c1e9dcc688065fc297e99fd876e4451373045dc834ae59a8b27d0a770af; Path=/; Secure; HTTPOnly, TS01be1219=017a39551596eb9099335eba30073ad2c0f7af45500d3f70d876760aa8e3f604be689a54508f8b884c5c2dfef266c297d630898ec3; path=/; domain=www.birmingham.gov.uk; HTTPonly; Secure","Strict-Transport-Security":"max-age=2592000","Vary":"Host","Via":"1.1 dca1-bit14","X-Content-Type-Options":"nosniff","X-Frame-Options":"SAMEORIGIN","X-XSS-Protection":"1; mode=block"},"status":"200","url":"https://www.birmingham.gov.uk/download/downloads/id/9037/brownfield_register.csv"}