{"dataset":"brownfield-land","datetime":"2020-05-04T00:11:22.420114","elapsed":"0.44","organisation":"local-authority-eng:SND","request-headers":{"Accept":"*/*","Accept-Encoding":"gzip, deflate","Connection":"keep-alive","User-Agent":"Digital Land data collector"},"resource":"e91a0e5bf7accaf40bb0bf4c1aa5c287c79ac9577db89034b99b482991936a56","response-headers":{"Accept-Ranges":"bytes","Cache-Control":"private","Content-Encoding":"gzip","Content-Length":"5222","Content-Type":"text/csv","Date":"Mon, 04 May 2020 00:11:21 GMT","ETag":"5957D98ABA9C9965819F26C56FA3DEF2","Expires":"Mon, 01 Jun 2020 00:11:22 GMT","Last-Modified":"Wed, 19 Dec 2018 12:33:05 GMT","Vary":"If-Modified-Since, If-None-Match","X-AspNetMvc-Version":"5.2","X-Content-Type-Options":"nosniff","X-Frame-Options":"SAMEORIGIN"},"status":"200","url":"https://www.sunderland.gov.uk/media/21020/Sunderland-brownfield-register-2018-12-01-rev1-csv-/CSV/sunderland_brownfieldregister_2018-12-01_rev1_csv1.csv?"}