{"dataset":"brownfield-land","datetime":"2019-12-13T01:26:56.987522","elapsed":"0.278","organisation":"local-authority-eng:ROC","request-headers":{"Accept":"*/*","Accept-Encoding":"gzip, deflate","Connection":"keep-alive","User-Agent":"Digital Land data collector"},"resource":"d5f77b7006fb5c10cdbd994bce322392e307d432a7eb2a894131496cb8daa014","response-headers":{"Accept-Ranges":"bytes","Connection":"keep-alive","Content-Length":"226979","Content-Type":"application/pdf","Date":"Fri, 13 Dec 2019 01:26:57 GMT","ETag":"\"5c5da10d-376a3\"","Last-Modified":"Fri, 08 Feb 2019 15:32:29 GMT","Server":"nginx","Set-Cookie":"AWSALB=/QXO0H6ewimBqeVBvsbkth8j5DpByIxkoXDEi5ClGcPfQ/+hNmIdlD+oeG0ISPPDvYuzCKSUg4R2BZJBrEcmRbZxlBAetZnhbh3WhWQ10MlEhQN/7A7q8EiOrFwy; Expires=Fri, 20 Dec 2019 01:26:57 GMT; Path=/"},"status":"200","url":"https://www.rochford.gov.uk/sites/default/files/RDC_BrownfieldLandRegister2019.pdf"}