{"dataset":"brownfield-land","datetime":"2020-05-26T00:36:00.738994","elapsed":"0.53","organisation":"local-authority-eng:SNO","request-headers":{"Accept":"*/*","Accept-Encoding":"gzip, deflate","Connection":"keep-alive","User-Agent":"Digital Land data collector"},"resource":"adf8270cdde8dd059990e8fce07b6a6d352b21fca949fc9baf0ab679e7f4fb6b","response-headers":{"Accept-Ranges":"bytes","Age":"6954","Cache-Control":"max-age=1209600","Connection":"keep-alive","Content-Length":"16337","Content-Type":"text/csv","Date":"Tue, 26 May 2020 00:36:01 GMT","Expires":"Mon, 08 Jun 2020 22:40:06 GMT","Last-Modified":"Fri, 06 Apr 2018 12:01:05 GMT","Server":"nginx","Via":"varnish","X-AH-Environment":"prod","X-Cache":"HIT","X-Cache-Hits":"2","X-Content-Type-Options":"nosniff","X-Request-ID":"v-ae822bf4-9ed8-11ea-9449-c37841ec0cea"},"status":"200","url":"https://www.south-norfolk.gov.uk/sites/default/files/downloads/southnorfolk_brownfieldregister_2017-12-31_rev1.csv"}