{"dataset":"brownfield-land","datetime":"2019-12-20T06:46:59.842554","elapsed":"1.325","organisation":"local-authority-eng:SWK","request-headers":{"Accept":"*/*","Accept-Encoding":"gzip, deflate","Connection":"keep-alive","User-Agent":"Digital Land data collector"},"resource":"314a6fc71008dd8e91a2e7420b73ad3616a8ed8c76863e30fe5d7f1cf7d938eb","response-headers":{"Cache-Control":"private","Content-Disposition":"attachment; filename=\"Southwark Brownfield 2017.xlsx\"","Content-Length":"96485","Content-Type":"application/vnd.openxmlformats-officedocument.spreadsheetml.sheet","Date":"Fri, 20 Dec 2019 06:46:45 GMT","Set-Cookie":"visid_incap_1892657=ztzXGPSRTD6uyU8BJuvZQWNu/F0AAAAAQUIPAAAAAAAW6QIFC4QjOXBwFG9fbA5o; expires=Fri, 18 Dec 2020 08:38:56 GMT; path=/; Domain=.southwark.gov.uk, incap_ses_47_1892657=OyV2YWnFtCw+Oz+WwPymAGRu/F0AAAAA+hyrHlnVfh/ZFyPneEET+Q==; path=/; Domain=.southwark.gov.uk","X-CDN":"Incapsula","X-Iinfo":"8-165608514-165608533 NNNN CT(12 12 0) RT(1576824419809 40) q(0 0 0 0) r(2 2) U5","X-Powered-By":"ASP.NET"},"status":"200","url":"https://www.southwark.gov.uk/assets/attach/5763/Southwark-Brownfield-2017.xlsx"}