{"dataset":"brownfield-land","datetime":"2020-01-02T07:08:35.681231","elapsed":"0.671","organisation":"local-authority-eng:KIR","request-headers":{"Accept":"*/*","Accept-Encoding":"gzip, deflate","Connection":"keep-alive","Cookie":"ASPSESSIONIDSECCDTSS=NGJMHECCOFNPAIEDANOLIMGB; visid_incap_1963062=CWj4o5tqSuqeXwSXFy+sY/OWDV4AAAAAQUIPAAAAAAAkZ/5N9aJQA3uymJ9X9zvC; incap_ses_872_1963062=n5ZRasloyEJeS4KHTPgZDPOWDV4AAAAAON1VDwt+RGnhKSNC+lYGgw==","User-Agent":"Digital Land data collector"},"resource":"9889f0273db6a79ccc162a6da6935788c27dd34b970875c51a204d1915da5cc3","response-headers":{"Accept-Ranges":"bytes","Content-Length":"58480","Content-Security-Policy":"frame-ancestors 'none';","Content-Type":"application/octet-stream","Date":"Thu, 02 Jan 2020 07:08:36 GMT","ETag":"\"946ec63c0b5d51:0\"","Last-Modified":"Wed, 18 Dec 2019 16:27:17 GMT","Server":"Microsoft-IIS/7.5","X-CDN":"Incapsula","X-Frame-Options":"SAMEORIGIN","X-Iinfo":"13-457203843-457203857 SNNy RT(1577948915917 82) q(0 1 1 -1) r(1 1) U12","X-UA-Compatible":"IE=edge"},"status":"200","url":"https://www.kirklees.gov.uk/brownfieldlandregister"}