{"dataset":"brownfield-land","datetime":"2020-01-26T01:19:06.431770","elapsed":"0.659","organisation":"local-authority-eng:DER","request-headers":{"Accept":"*/*","Accept-Encoding":"gzip, deflate","Connection":"keep-alive","User-Agent":"Digital Land data collector"},"resource":"777b5e1e380b516359eb70605aee15b4f502a52005b239f5857dbdef6949ce45","response-headers":{"Accept-Ranges":"bytes","Cache-Control":"no-cache,public","Content-Length":"15889","Content-Type":"application/octet-stream","Date":"Sun, 26 Jan 2020 01:19:07 GMT","ETag":"\"beed9c27c7d51:0\"","Last-Modified":"Thu, 09 Jan 2020 16:08:19 GMT","Server":"Microsoft-IIS/10.0","X-Powered-By":"ASP.NET","X-UA-Compatible":"IE=edge"},"status":"200","url":"https://www.derby.gov.uk/media/derbycitycouncil/contentassets/documents/policiesandguidance/planning/Brownfield_Reg_2019.csv"}