{"dataset":"brownfield-land","datetime":"2020-07-20T00:18:35.099766","elapsed":"2.518","organisation":"national-park-authority:Q72617669","request-headers":{"Accept":"*/*","Accept-Encoding":"gzip, deflate","Connection":"keep-alive","User-Agent":"Digital Land data collector"},"response-headers":{"Cache-Control":"private, max-age=0","Connection":"keep-alive","Content-Encoding":"gzip","Content-Type":"text/html; charset=utf-8","Date":"Mon, 20 Jul 2020 00:18:37 GMT","Expires":"Mon, 20 Jul 2020 00:48:35 GMT","Pragma":"cache","Server":"openresty","Set-Cookie":"SQ_SYSTEM_SESSION=icq33ngcrq0cr5cfmgk45vaj2n1sdoacchk62ptg3mvfefn8m9ujqmbn726m0jmp3rpgcu3ekgjdriv09cj0fthupblk5gm9du5dhj1; path=/; secure; HttpOnly","Transfer-Encoding":"chunked","Vary":"Accept-Encoding, Accept-Encoding","Via":"1.1 np-web01.ash2.squiz.cloud","X-Cache":"MISS from np-web01.ash2.squiz.cloud","X-Content-Type-Options":"nosniff","X-Frame-Options":"SAMEORIGIN","X-Request-ID":"b27a6cba-94b4-444c-b05b-39bda31012dc","X-upgrade-enabled":"off"},"status":"404","url":"https://www.northyorkmoors.org.uk/__data/assets/file/0007/1429792/north-york-moors_brownfieldregister_2019-12-17_rev1.csv"}