{"dataset":"brownfield-land","datetime":"2019-11-03T06:40:30.899876","elapsed":"0.253","organisation":"local-authority-eng:LUT","request-headers":{"Accept":"*/*","Accept-Encoding":"gzip, deflate","Connection":"keep-alive","Cookie":"__cfduid=dbfb127adb94326cdea7fa63f5747552d1572763230","User-Agent":"Digital Land data collector"},"resource":"d592c9c125651be573b8528b3334920b98dedc1388c589abf5227249dae847e1","response-headers":{"Accept-Ranges":"bytes","CF-Cache-Status":"MISS","CF-RAY":"52fc5b72185c345c-LHR","Cache-Control":"public, max-age=14400","Connection":"keep-alive","Content-Length":"61840","Content-Type":"application/octet-stream","Date":"Sun, 03 Nov 2019 06:40:31 GMT","ETag":"\"{5260DA4A-A1FA-4AE4-9B95-20BEABEB3BA5},6\"","Expect-CT":"max-age=604800, report-uri=\"https://report-uri.cloudflare.com/cdn-cgi/beacon/expect-ct\"","Expires":"Sun, 03 Nov 2019 10:40:31 GMT","Last-Modified":"Mon, 21 Jan 2019 15:40:45 GMT","Public-Extension":"http://schemas.microsoft.com/repl-2","ResourceTag":"rt:5260DA4A-A1FA-4AE4-9B95-20BEABEB3BA5@00000000006","Server":"cloudflare","Vary":"Accept-Encoding","X-MS-InvokeApp":"1; RequireReadOnly"},"status":"200","url":"http://www.luton.gov.uk/Environment/Lists/LutonDocuments/Excel/HOU-014.csv"}