{"dataset":"brownfield-land","datetime":"2020-05-24T00:31:25.442990","elapsed":"0.776","organisation":"local-authority-eng:CAR","request-headers":{"Accept":"*/*","Accept-Encoding":"gzip, deflate","Connection":"keep-alive","User-Agent":"Digital Land data collector"},"response-headers":{"CF-Cache-Status":"DYNAMIC","CF-RAY":"5982e9e958ae9f46-IAD","Cache-Control":"private","Connection":"keep-alive","Content-Encoding":"gzip","Content-Type":"text/html; charset=utf-8","Date":"Sun, 24 May 2020 00:31:26 GMT","Expect-CT":"max-age=604800, report-uri=\"https://report-uri.cloudflare.com/cdn-cgi/beacon/expect-ct\"","Server":"cloudflare","Set-Cookie":"__cfduid=db71afac731f9511e0ee5c30df9cda4ec1590280285; expires=Tue, 23-Jun-20 00:31:25 GMT; path=/; domain=.carlisle.gov.uk; HttpOnly; SameSite=Lax, dnn_IsMobile=False; path=/; secure; HttpOnly; SameSite=lax, language=en-GB; path=/; secure; HttpOnly; SameSite=lax, .ASPXANONYMOUS=UnHgfvRn1gEkAAAAMzUxMDZhMmYtMGY0OC00NjMxLWI3YWItNjZmZWRkMzNhODIz0; expires=Sat, 01-Aug-2020 11:11:25 GMT; path=/; HttpOnly; SameSite=lax, Analytics_VisitorId=2e792b28-e18e-425d-ad72-9ce27196cbb8; expires=Tue, 23-Jun-2020 00:31:25 GMT; path=/; secure; HttpOnly; SameSite=lax, Analytics=SessionId=&TabId=2083&ContentItemId=-1; expires=Sun, 24-May-2020 01:31:25 GMT; path=/; secure; HttpOnly; SameSite=lax, __RequestVerificationToken=jUDooDkftuWsSydBLqRG9KXXeBiVpEVDLxnEM8LGTkZQZe-xMj1y4ngrqV-d9NotEdT0ssgQ57_EM4zO1o_WQ6kde8hAc3WF7yQr8mEQ2vq9Q7_u5O89UexUUtQ1; path=/; secure; HttpOnly; SameSite=lax","Transfer-Encoding":"chunked","X-AspNet-Version":"4.0.30319","X-Powered-By":"ASP.NET","X-UA-Compatible":"IE=edge, IE=edge","cf-request-id":"02e5b085da00009f46b1a2a200000001"},"status":"200","url":"https://www.carlisle.gov.uk/planning-policy/Evidence-Base/Brownfield-Register#"}