{"dataset":"brownfield-land","datetime":"2020-05-18T00:10:59.726212","elapsed":"0.162","organisation":"local-authority-eng:SOX","request-headers":{"Accept":"*/*","Accept-Encoding":"gzip, deflate","Connection":"keep-alive","User-Agent":"Digital Land data collector"},"response-headers":{"Connection":"Keep-Alive","Content-Length":"281","Content-Type":"text/html; charset=iso-8859-1","Date":"Mon, 18 May 2020 00:10:59 GMT","Keep-Alive":"timeout=15, max=100","Server":"Apache"},"status":"403","url":"http://www.southoxon.gov.uk/sites/default/files/2018_12_21%20Brownfield%20Register_South%20Oxfordshire.csv"}