{"dataset":"brownfield-land","datetime":"2020-06-19T00:09:32.255465","elapsed":"0.464","organisation":"local-authority-eng:ERE","request-headers":{"Accept":"*/*","Accept-Encoding":"gzip, deflate","Connection":"keep-alive","User-Agent":"Digital Land data collector"},"resource":"7fc43a5ccb6d7adde6a0ebbcffe93cf2b27beb1a287b18692d9e00b6d78bd8c6","response-headers":{"Accept-Ranges":"bytes","Connection":"Keep-Alive","Content-Length":"22095","Content-Type":"application/vnd.openxmlformats-officedocument.spreadsheetml.sheet","Date":"Fri, 19 Jun 2020 00:09:32 GMT","Keep-Alive":"timeout=1, max=30","Last-Modified":"Tue, 31 Dec 2019 13:03:30 GMT","Server":"Apache"},"status":"200","url":"https://www.erewash.gov.uk/media/EBC/web-files/planning/brownfield-land.csv.xlsx"}