{"dataset":"brownfield-land","datetime":"2020-08-01T00:11:55.299808","elapsed":"0.542","organisation":"local-authority-eng:BEN","request-headers":{"Accept":"*/*","Accept-Encoding":"gzip, deflate","Connection":"keep-alive","User-Agent":"Digital Land data collector"},"response-headers":{"Cache-Control":"private","Content-Length":"16816","Content-Type":"text/html; charset=utf-8","Date":"Sat, 01 Aug 2020 00:12:33 GMT","Strict-Transport-Security":"max-age=31536000; includeSubDomains; preload","X-AspNet-Version":"4.0.30319","X-Content-Type-Options":"nosniff","X-Frame-Options":"ALLOW-FROM https://lbdigitalservices.sharepoint.com","X-XSS-Protection":"1"},"status":"200","url":"https://www.brent.gov.uk/media/16412569/brownfield-register-web.xlsx"}