{"dataset":"brownfield-land","datetime":"2020-06-16T00:08:00.334571","elapsed":"0.624","organisation":"local-authority-eng:BRC","request-headers":{"Accept":"*/*","Accept-Encoding":"gzip, deflate","Connection":"keep-alive","User-Agent":"Digital Land data collector"},"resource":"44afe322697927031cfba057e2902cde48e259ac53ee532726abf01b10a85156","response-headers":{"Accept-Ranges":"bytes","Connection":"keep-alive","Content-Length":"15485","Content-Type":"application/vnd.openxmlformats-officedocument.spreadsheetml.sheet","Date":"Tue, 16 Jun 2020 00:08:00 GMT","ETag":"\"5dfcb9c5-3c7d\"","Last-Modified":"Fri, 20 Dec 2019 12:08:37 GMT","Server":"nginx","Via":"1.1 5eb5e19c1a78889d10ff38f1551ed2aa.cloudfront.net (CloudFront)","X-Amz-Cf-Id":"YCwelDe-cD3HuOWBDnhTloBsTE8Q1LC1HKUPfSwuLGOnWLPuMjK3BA==","X-Amz-Cf-Pop":"IAD89-C1","X-Cache":"Miss from cloudfront","X-Debug-Info":"eyJyZXRyaWVzIjowfQ==","X-Platform-Server":"i-04ca136c4b441e805","X-Request-Id":"3afddr7q67wwmghuibmsfjs4"},"status":"200","url":"https://www.bracknell-forest.gov.uk/sites/default/files/documents/brownfield-register-2019.xlsx"}