{"dataset":"brownfield-land","datetime":"2020-06-09T00:11:09.295248","elapsed":"1.296","organisation":"local-authority-eng:MAV","request-headers":{"Accept":"*/*","Accept-Encoding":"gzip, deflate","Connection":"keep-alive","Cookie":"a4a33b4e89d8929463a6f6c5a60e359d=1b3b5e3bf77d01e6e6b04ab9975bc57e","User-Agent":"Digital Land data collector"},"response-headers":{"Cache-Control":"no-store, no-cache, must-revalidate, post-check=0, pre-check=0, public","Connection":"close","Content-Encoding":"gzip","Content-Length":"6106","Content-Type":"text/html; charset=utf-8","Date":"Tue, 09 Jun 2020 00:11:10 GMT","Expires":"Wed, 17 Aug 2005 00:00:00 GMT","Last-Modified":"Tue, 09 Jun 2020 00:11:10 GMT","Pragma":"no-cache","Server":"Apache","Set-Cookie":"rl_modals=1; expires=Wed, 09-Jun-2021 00:11:10 GMT; Max-Age=31536000; path=/","Vary":"Accept-Encoding","X-Content-Type-Options":"nosniff"},"status":"200","url":"https://www.malvernhills.gov.uk/documents/283188/8873213/MalvernHillsBrownfieldLandRegister2017csv.csv/bfef9d76-453a-b239-de88-e24b02a172db"}