{"dataset":"brownfield-land","datetime":"2020-01-20T01:24:23.793755","elapsed":"1.35","organisation":"local-authority-eng:WFT","request-headers":{"Accept":"*/*","Accept-Encoding":"gzip, deflate","Connection":"keep-alive","Cookie":"device=3; device_type=0; SSESS6662e7a308dd6c21d2dbdf87dadca3a3=RAWjtQagsUiNNqfjkzUSFyOFHMy1UzrgCOuGfhJlmWM; SESS6662e7a308dd6c21d2dbdf87dadca3a3=s_xHAwqieLxcMP4JezQCQQ5svTuhOV3gfuIbaAtGmTc","User-Agent":"Digital Land data collector"},"resource":"f548f09d34f67ebcc13a9ac49a767efb5a2b42ad260eee5c39b0cd30a2121b40","response-headers":{"Accept-Ranges":"bytes, bytes","Age":"0","Cache-Control":"max-age=1209600","Connection":"keep-alive","Content-Length":"17377","Content-Type":"text/csv","Date":"Mon, 20 Jan 2020 01:24:25 GMT","ETag":"\"43e1-57045610bc568\"","Expires":"Mon, 03 Feb 2020 01:24:25 GMT","Last-Modified":"Thu, 05 Jul 2018 19:16:06 GMT","Server":"Apache","Via":"1.1 varnish-v4","X-Content-Type-Options":"nosniff","X-Varnish":"1511420"},"status":"200","url":"https://www.walthamforest.gov.uk/node/4007"}