{"dataset":"brownfield-land","datetime":"2020-11-01T00:11:44.669184","elapsed":"0.692","organisation":"local-authority-eng:COV","request-headers":{"Accept":"*/*","Accept-Encoding":"gzip, deflate","Connection":"keep-alive","User-Agent":"Digital Land data collector"},"resource":"ec1ff31625d546423b174d6e6eafca40efa4f10525199b0cbc6990ceb7d748a9","response-headers":{"CF-Cache-Status":"DYNAMIC","CF-RAY":"5eb16675fced0994-IAD","Cache-Control":"must-revalidate, post-check=0, pre-check=0","Connection":"keep-alive","Content-Disposition":"attachment; filename=\"BrownfieldLandRegister.xlsm\"","Content-Length":"91177","Content-Type":"application/vnd.ms-excel.sheet.macroenabled.12","Date":"Sun, 01 Nov 2020 00:11:45 GMT","ETag":"\"16429-58346a7940b80\"","Expect-CT":"max-age=604800, report-uri=\"https://report-uri.cloudflare.com/cdn-cgi/beacon/expect-ct\"","Expires":"Mon, 26 Jul 1997 05:00:00 GMT","Last-Modified":"Mon, 04 Mar 2019 15:46:06 GMT","Node":"jadu-web-1","Pragma":"no-cache","Server":"cloudflare","Set-Cookie":"__cfduid=d3ff2a331e3a1828030f20e0e8f797ebd1604189504; expires=Tue, 01-Dec-20 00:11:44 GMT; path=/; domain=.coventry.gov.uk; HttpOnly; SameSite=Lax, PHPSESSID=ENqEGf0nfc3T25dkWI8wvlCV9AldR9jDz-HD76PhBscWlEDfgG72xa1f-h-1dwQ8; path=/; secure; HttpOnly, TestCookie=Test; path=/; domain=www.coventry.gov.uk; HttpOnly","Strict-Transport-Security":"max-age=2592000","X-Content-Type-Options":"nosniff","X-Frame-Options":"SAMEORIGIN","X-XSS-Protection":"1; mode=block","cf-request-id":"0622be5dba000009941c2ed000000001"},"status":"200","url":"https://www.coventry.gov.uk/download/downloads/id/27571/brownfield_land_register.xlsm"}