{"dataset":"brownfield-land","datetime":"2020-05-16T00:08:45.054223","elapsed":"1.059","organisation":"local-authority-eng:NUN","request-headers":{"Accept":"*/*","Accept-Encoding":"gzip, deflate","Connection":"keep-alive","User-Agent":"Digital Land data collector"},"resource":"f71f167a5a41162561300694c257c15fa064ccf9378e8cc99da98179960cef1d","response-headers":{"Cache-Control":"must-revalidate, post-check=0, pre-check=0","Content-Disposition":"attachment; filename=\"Brownfield_land.csv\"","Content-Length":"35313","Content-Type":"application/vnd.ms-excel","Date":"Sat, 16 May 2020 00:08:47 GMT","Expires":"Mon, 26 Jul 1997 05:00:00 GMT","Pragma":"public","Server":"Microsoft-IIS/8.5","Set-Cookie":"PHPSESSID=42c26422e313b777da87a3947c63a018; path=/; secure; HttpOnly, TestCookie=Test; path=/; domain=www.nuneatonandbedworth.gov.uk; HttpOnly","Strict-Transport-Security":"max-age=2592000","X-FRAME-OPTIONS":"SAMEORIGIN","X-Powered-By":"ASP.NET"},"status":"200","url":"https://www.nuneatonandbedworth.gov.uk/download/downloads/id/2209/nuneaton_and_bedworth_brownfield_register_-_csv_2019.csv"}