{"dataset":"brownfield-land","datetime":"2019-11-29T11:05:50.600756","elapsed":"1.037","organisation":"local-authority-eng:KWL","request-headers":{"Accept":"*/*","Accept-Encoding":"gzip, deflate","Connection":"keep-alive","Cookie":"CMSPreferredCulture=en-GB; CMSCsrfCookie=YVYvqxR4y3t9etWuwoIk3EmTPs7+9opMkdrWC0VM; ASP.NET_SessionId=rdc4bvgt3ckwbftwx1aqhdgf; AWSELB=8FBD93611AA20F76EA012D7D56060E4829BEF70B32B3CB116CC531708826A02135EB3D081CDFF16DF35E8CA1220B23AEBD77E4DCDAFB4D355EA5FC2BE1A7B8CB24B2469C23","User-Agent":"Digital Land data collector"},"response-headers":{"Cache-Control":"private, no-store, must-revalidate","Connection":"keep-alive","Content-Encoding":"deflate","Content-Length":"96242","Content-Type":"text/html; charset=utf-8","Date":"Fri, 29 Nov 2019 11:16:23 GMT","Server":"Microsoft-IIS/7.5","Set-Cookie":"CMSPreferredCulture=en-GB; expires=Sun, 29-Nov-2020 11:16:24 GMT; path=/; HttpOnly, CMSCurrentTheme=Global; expires=Sat, 30-Nov-2019 11:16:24 GMT; path=/; HttpOnly, CMSPreferredUICulture=; expires=Thu, 29-Nov-2018 11:16:24 GMT; path=/; HttpOnly","Vary":"Accept-Encoding","X-AspNet-Version":"4.0.30319","X-Frame-Options":"SAMEORIGIN","X-Powered-By":"ASP.NET","X-UA-Compatible":"IE=Edge"},"status":"404","url":"http://www.knowsley.gov.uk/knowsleycouncil/media/Documents/Knowsley-MBC-Brownfield-register.xlsx"}