{"dataset":"brownfield-land","datetime":"2020-03-31T00:10:04.945575","elapsed":"0.665","organisation":"local-authority-eng:MAN","request-headers":{"Accept":"*/*","Accept-Encoding":"gzip, deflate","Connection":"keep-alive","User-Agent":"Digital Land data collector"},"resource":"8d701ad64b94c5ae2bb52c131d620b419be57c51a787f56de715a4da7efd3e99","response-headers":{"Accept-Ranges":"bytes","Connection":"Keep-Alive","Content-Length":"136352","Content-Type":"text/csv","Date":"Tue, 31 Mar 2020 00:13:29 GMT","ETag":"\"214a0-57f2c60b02b40\"","Keep-Alive":"timeout=5, max=100","Last-Modified":"Fri, 11 Jan 2019 10:44:21 GMT","Server":"Apache/2.4.7 (Ubuntu)"},"status":"200","url":"http://inspire.misoportal.com/csv/files/manchester_city_council/manchester_brownfield_register_31st_march_2018.csv"}