{"dataset":"brownfield-land","datetime":"2020-04-11T00:04:58.819455","elapsed":"1.168","organisation":"local-authority-eng:CAT","request-headers":{"Accept":"*/*","Accept-Encoding":"gzip, deflate","Connection":"keep-alive","User-Agent":"Digital Land data collector"},"resource":"da787466995e063f8e2c510c82b805cd1e28e229227540cc63287abe00bd2a18","response-headers":{"CF-Cache-Status":"DYNAMIC","CF-RAY":"5820740e3aedea38-IAD","Cache-Control":"must-revalidate, post-check=0, pre-check=0","Connection":"keep-alive","Content-Disposition":"attachment; filename=\"brownfield_land.csv\"","Content-Length":"21645","Content-Type":"text/csv;charset=UTF-8","Date":"Sat, 11 Apr 2020 00:04:59 GMT","Expect-CT":"max-age=604800, report-uri=\"https://report-uri.cloudflare.com/cdn-cgi/beacon/expect-ct\"","Expires":"Mon, 26 Jul 1997 05:00:00 GMT","Node":"jadu-web-1","Pragma":"public","Server":"cloudflare","Set-Cookie":"__cfduid=d0d9a5c0904723e21e0b5df2623b82bf61586563499; expires=Mon, 11-May-20 00:04:59 GMT; path=/; domain=.canterbury.gov.uk; HttpOnly; SameSite=Lax, PHPSESSID=pXsohjltzZRCNSSpL7r88wG9p3NRPMCWhw36MPEyIdd12VjYScYpoOpOKT18o9T1; path=/; secure; HttpOnly, TestCookie=Test; path=/; domain=www.canterbury.gov.uk; HttpOnly","Strict-Transport-Security":"max-age=2592000","X-Content-Type-Options":"nosniff","X-Frame-Options":"SAMEORIGIN","X-XSS-Protection":"1; mode=block"},"status":"200","url":"https://www.canterbury.gov.uk/download/downloads/id/1217/canterbury_brownfield_land_register.csv"}