{"dataset":"brownfield-land","datetime":"2020-07-11T00:17:06.895762","elapsed":"1.166","organisation":"local-authority-eng:SOS","request-headers":{"Accept":"*/*","Accept-Encoding":"gzip, deflate","Connection":"keep-alive","Cookie":"__cfduid=dbcc95ccdc539add11f7790ab80461a8f1594426627","User-Agent":"Digital Land data collector"},"response-headers":{"CF-Cache-Status":"DYNAMIC","CF-RAY":"5b0e56f5aa83f0d9-IAD","Cache-Control":"no-cache","Connection":"keep-alive","Content-Encoding":"gzip","Content-Type":"text/html; charset=UTF-8","Date":"Sat, 11 Jul 2020 00:17:08 GMT","Expect-CT":"max-age=604800, report-uri=\"https://report-uri.cloudflare.com/cdn-cgi/beacon/expect-ct\"","Node":"jadu-web-1","Server":"cloudflare","Set-Cookie":"PHPSESSID=eFZrVuu5hI8IlSD7xv9PKknYMDYivR%2CPzl4GuCBYb4OnBZOnoHWikGE6JSsuMS4e; path=/; secure; HttpOnly","Transfer-Encoding":"chunked","X-Content-Type-Options":"nosniff","X-Frame-Options":"SAMEORIGIN","X-XSS-Protection":"1; mode=block","cf-request-id":"03dcd4ad8d0000f0d95bbf8200000001"},"status":"404","url":"http://www.southend.gov.uk/download/downloads/id/5346/southend_brownfield_register_2017-03-31_rev1.csv"}